statar/__init__.py
statar/__main__.py
statar/_attrs.py
statar/_core.py
statar/_format.py
statar/_ops.py
statar/_sem.py
statar/_util.py
statar/app.py
statar/version.py
statar-0.8.1.data/scripts/statar
statar-0.8.1.dist-info/LICENSE.txt
statar-0.8.1.dist-info/METADATA
statar-0.8.1.dist-info/WHEEL
statar-0.8.1.dist-info/top_level.txt
statar-0.8.1.dist-info/RECORD
